aisberg/__init__.py
aisberg/async_client.py
aisberg/client.py
aisberg/config.py
aisberg/exceptions.py
aisberg/utils.py
aisberg/abstract/__init__.py
aisberg/abstract/modules.py
aisberg/api/__init__.py
aisberg/api/async_endpoints.py
aisberg/api/endpoints.py
aisberg/models/__init__.py
aisberg/models/chat.py
aisberg/models/collections.py
aisberg/models/documents.py
aisberg/models/embeddings.py
aisberg/models/models.py
aisberg/models/requests.py
aisberg/models/token.py
aisberg/models/tools.py
aisberg/models/workflows.py
aisberg/modules/__init__.py
aisberg/modules/chat.py
aisberg/modules/collections.py
aisberg/modules/documents.py
aisberg/modules/embeddings.py
aisberg/modules/me.py
aisberg/modules/models.py
aisberg/modules/tools.py
aisberg/modules/workflows.py
aisberg/requests/__init__.py
aisberg/requests/async_requests.py
aisberg/requests/sync_requests.py
aisberg-0.4.4.dist-info/licenses/LICENSE
aisberg-0.4.4.dist-info/METADATA
aisberg-0.4.4.dist-info/WHEEL
aisberg-0.4.4.dist-info/top_level.txt
aisberg-0.4.4.dist-info/RECORD
