Metadata-Version: 2.4
Name: aisberg
Version: 0.4.4
Summary: Aisberg SDK for Python - A simple and powerful SDK to interact with the Aisberg API
Author: Free Pro
Author-email: Mathis Lambert <mathis.lambert@freepro.com>
License: Private License
Classifier: Programming Language :: Python :: 3.10
Classifier: Programming Language :: Python :: 3.12
Classifier: Programming Language :: Python :: 3.13
Classifier: Operating System :: OS Independent
Classifier: License :: Other/Proprietary License
Requires-Python: >=3.10
License-File: LICENSE
Requires-Dist: httpx>=0.28.1
Requires-Dist: pydantic>=2.11.7
Requires-Dist: pydantic-settings>=2.10.1
Provides-Extra: test
Requires-Dist: pytest>=8.4.1; extra == "test"
Requires-Dist: pytest-asyncio>=1.0.0; extra == "test"
Requires-Dist: pytest-cov>=6.2.1; extra == "test"
Requires-Dist: pytest-mock>=3.14.1; extra == "test"
Provides-Extra: dev
Requires-Dist: black>=25.1.0; extra == "dev"
Requires-Dist: isort>=6.0.1; extra == "dev"
Requires-Dist: mypy>=1.16.1; extra == "dev"
Requires-Dist: flake8>=7.3.0; extra == "dev"
Dynamic: license-file
